stashcache_tester
