Metadata-Version: 1.1
Name: stashcache-tester
Version: 0.2.0
Summary: A tester for the StashCache infrastructure
Home-page: https://github.com/djw8605/stashcache-tester
Author: Derek Weitzel
Author-email: dweitzel@cse.unl.edu
License: Apache 2.0
Keywords: StashCache testing
Platform: UNKNOWN
Classifier: Development Status :: 3 - Alpha
Classifier: Topic :: Utilities
